topsis.py
Topsis_Harjot_102017126-1.0.1.dist-info/METADATA
Topsis_Harjot_102017126-1.0.1.dist-info/WHEEL
Topsis_Harjot_102017126-1.0.1.dist-info/desktop.ini
Topsis_Harjot_102017126-1.0.1.dist-info/entry_points.txt
Topsis_Harjot_102017126-1.0.1.dist-info/top_level.txt
Topsis_Harjot_102017126-1.0.1.dist-info/RECORD
