Metadata-Version: 2.1
Name: Topsis-Harjot-102017126
Version: 1.0.1
Summary: A Python package implementing TOPSIS for MCDM
Home-page: https://github.com/HarryGrewal9/Topsis-Harjot-102017126
Download-URL: https://github.com/HarryGrewal9/Topsis-Harjot-102017126/archive/refs/tags/v_01.tar.gz
Author: Harjot tSingh
License: MIT
Keywords: python,TOPSIS,MCDM,MCDA,statistics,prescriptive analytics,cli
Classifier: License :: OSI Approved :: MIT License
Classifier: Programming Language :: Python :: 3
Classifier: Programming Language :: Python :: 3.7
Requires-Dist: numpy
Requires-Dist: pandas
